{
  "updatedAt": "2026-07-23T09:14:00-03:00",
  "games": [
    {
      "date": "2026-07-23",
      "time": "19:00",
      "home": "Bolívar",
      "away": "Grêmio",
      "competition": "Sul-Americana",
      "round": "Playoffs (Ida)",
      "channel": "Paramount+",
      "stadium": "Estadio Hernando Siles, La Paz"
    },
    {
      "date": "2026-07-23",
      "time": "19:30",
      "home": "Athletic",
      "away": "São Bernardo",
      "competition": "Brasileirão Série B",
      "round": "Rodada 19",
      "channel": "ESPN / Disney+",
      "stadium": "Estádio Joaquim Portugal"
    },
    {
      "date": "2026-07-23",
      "time": "19:30",
      "home": "Botafogo",
      "away": "Vitória",
      "competition": "Brasileirão Série A",
      "round": "Rodada 4 (adiado)",
      "channel": "Record / CazéTV / Premiere",
      "stadium": "Estádio Nilton Santos"
    },
    {
      "date": "2026-07-23",
      "time": "19:30",
      "home": "Corinthians",
      "away": "Remo",
      "competition": "Brasileirão Série A",
      "round": "Rodada 19",
      "channel": "SporTV / Premiere",
      "stadium": "Neo Química Arena"
    },
    {
      "date": "2026-07-23",
      "time": "20:30",
      "home": "Cuiabá",
      "away": "Atlético Goianiense",
      "competition": "Brasileirão Série B",
      "round": "Rodada 19",
      "channel": "ESPN / Disney+",
      "stadium": "Arena Pantanal"
    },
    {
      "date": "2026-07-23",
      "time": "21:30",
      "home": "Boca Juniors",
      "away": "O'Higgins",
      "competition": "Sul-Americana",
      "round": "Playoffs (Ida)",
      "channel": "ESPN / Disney+",
      "stadium": "La Bombonera, Buenos Aires"
    },
    {
      "date": "2026-07-23",
      "time": "21:30",
      "home": "Botafogo-SP",
      "away": "Juventude",
      "competition": "Brasileirão Série B",
      "round": "Rodada 19",
      "channel": "ESPN / Disney+",
      "stadium": "Estádio Santa Cruz"
    },
    {
      "date": "2026-07-23",
      "time": "21:30",
      "home": "Santa Fe",
      "away": "Caracas",
      "competition": "Sul-Americana",
      "round": "Playoffs (Ida)",
      "channel": "Paramount+",
      "stadium": "Estadio El Campín, Bogotá"
    },
    {
      "date": "2026-07-25",
      "time": "18:30",
      "home": "Athletico-PR",
      "away": "Internacional",
      "competition": "Brasileirão Série A",
      "round": "Rodada 20",
      "channel": "A definir",
      "stadium": "Arena da Baixada"
    },
    {
      "date": "2026-07-25",
      "time": "18:30",
      "home": "Santos",
      "away": "Chapecoense",
      "competition": "Brasileirão Série A",
      "round": "Rodada 20",
      "channel": "A definir",
      "stadium": "Vila Belmiro"
    },
    {
      "date": "2026-07-25",
      "time": "20:30",
      "home": "Vasco",
      "away": "Mirassol",
      "competition": "Brasileirão Série A",
      "round": "Rodada 20",
      "channel": "A definir",
      "stadium": "São Januário"
    },
    {
      "date": "2026-07-26",
      "time": "16:00",
      "home": "Bahia",
      "away": "Corinthians",
      "competition": "Brasileirão Série A",
      "round": "Rodada 20",
      "channel": "Globo / Premiere",
      "stadium": "Arena Fonte Nova, Salvador"
    },
    {
      "date": "2026-07-26",
      "time": "16:00",
      "home": "Criciúma",
      "away": "Náutico",
      "competition": "Brasileirão Série B",
      "round": "Rodada 20",
      "channel": "ESPN / Disney+",
      "stadium": "Estádio Heriberto Hülse, Criciúma"
    },
    {
      "date": "2026-07-26",
      "time": "16:00",
      "home": "Cruzeiro",
      "away": "Botafogo",
      "competition": "Brasileirão Série A",
      "round": "Rodada 20",
      "channel": "Globo / Premiere",
      "stadium": "Mineirão, Belo Horizonte"
    },
    {
      "date": "2026-07-26",
      "time": "16:00",
      "home": "São Bernardo",
      "away": "Ceará",
      "competition": "Brasileirão Série B",
      "round": "Rodada 20",
      "channel": "SporTV / Premiere",
      "stadium": "Estádio 1° de Maio"
    },
    {
      "date": "2026-07-26",
      "time": "18:30",
      "home": "América Mineiro",
      "away": "Goiás",
      "competition": "Brasileirão Série B",
      "round": "Rodada 20",
      "channel": "ESPN / Disney+",
      "stadium": "Estádio Raimundo Sampaio, Belo Horizonte"
    },
    {
      "date": "2026-07-26",
      "time": "18:30",
      "home": "Flamengo",
      "away": "São Paulo",
      "competition": "Brasileirão Série A",
      "round": "Rodada 20",
      "channel": "Globo / Premiere",
      "stadium": "Maracanã, Rio de Janeiro"
    },
    {
      "date": "2026-07-26",
      "time": "18:30",
      "home": "Grêmio",
      "away": "Fluminense",
      "competition": "Brasileirão Série A",
      "round": "Rodada 20",
      "channel": "A definir",
      "stadium": "Arena do Grêmio, Porto Alegre"
    },
    {
      "date": "2026-07-26",
      "time": "18:30",
      "home": "Londrina",
      "away": "Novorizontino",
      "competition": "Brasileirão Série B",
      "round": "Rodada 20",
      "channel": "ESPN / Disney+",
      "stadium": "Estádio VGD, Londrina"
    },
    {
      "date": "2026-07-26",
      "time": "18:30",
      "home": "Red Bull Bragantino",
      "away": "Coritiba",
      "competition": "Brasileirão Série A",
      "round": "Rodada 20",
      "channel": "A definir",
      "stadium": "Estádio Nabi Abi Chedid"
    },
    {
      "date": "2026-07-26",
      "time": "19:30",
      "home": "Palmeiras",
      "away": "Atlético-MG",
      "competition": "Brasileirão Série A",
      "round": "Rodada 20",
      "channel": "SporTV / Premiere",
      "stadium": "Nubank Parque"
    },
    {
      "date": "2026-07-26",
      "time": "19:30",
      "home": "Remo",
      "away": "Vitória",
      "competition": "Brasileirão Série A",
      "round": "Rodada 20",
      "channel": "A definir",
      "stadium": "Mangueirão, Belém"
    }
  ]
}
