{
  "updatedAt": "2026-06-29T13:14:00-03:00",
  "games": [
    {
      "date": "2026-06-29",
      "time": "14:00",
      "home": "Brasil",
      "away": "Japão",
      "competition": "Copa do Mundo 2026",
      "round": "16 avos de final",
      "channel": "Globo / SporTV / CazéTV",
      "stadium": "NRG Stadium"
    },
    {
      "date": "2026-06-29",
      "time": "17:30",
      "home": "Alemanha",
      "away": "Paraguai",
      "competition": "Copa do Mundo 2026",
      "round": "16 avos de final",
      "channel": "SporTV / CazéTV",
      "stadium": "Gillette Stadium"
    },
    {
      "date": "2026-06-29",
      "time": "22:00",
      "home": "Países Baixos",
      "away": "Marrocos",
      "competition": "Copa do Mundo 2026",
      "round": "16 avos de final",
      "channel": "CazéTV",
      "stadium": "Estadio BBVA"
    },
    {
      "date": "2026-06-30",
      "time": "14:00",
      "home": "Costa do Marfim",
      "away": "Noruega",
      "competition": "Copa do Mundo 2026",
      "round": "16 avos de final",
      "channel": "CazéTV",
      "stadium": "AT&T Stadium"
    },
    {
      "date": "2026-06-30",
      "time": "18:00",
      "home": "França",
      "away": "Suécia",
      "competition": "Copa do Mundo 2026",
      "round": "16 avos de final",
      "channel": "SporTV / CazéTV",
      "stadium": "MetLife Stadium"
    },
    {
      "date": "2026-06-30",
      "time": "20:00",
      "home": "Botafogo-SP",
      "away": "CRB",
      "competition": "Brasileirão Série B",
      "round": "Rodada 15",
      "channel": "Disney+",
      "stadium": "Estádio Santa Cruz"
    },
    {
      "date": "2026-06-30",
      "time": "22:00",
      "home": "México",
      "away": "Equador",
      "competition": "Copa do Mundo 2026",
      "round": "16 avos de final",
      "channel": "SporTV / CazéTV",
      "stadium": "Estadio Azteca"
    },
    {
      "date": "2026-07-01",
      "time": "13:00",
      "home": "Inglaterra",
      "away": "RD Congo",
      "competition": "Copa do Mundo 2026",
      "round": "16 avos de final",
      "channel": "SporTV / CazéTV",
      "stadium": "Mercedes-Benz Stadium"
    },
    {
      "date": "2026-07-01",
      "time": "17:00",
      "home": "Bélgica",
      "away": "Senegal",
      "competition": "Copa do Mundo 2026",
      "round": "16 avos de final",
      "channel": "CazéTV",
      "stadium": "Lumen Field"
    },
    {
      "date": "2026-07-01",
      "time": "21:00",
      "home": "Estados Unidos",
      "away": "Bósnia e Herzegovina",
      "competition": "Copa do Mundo 2026",
      "round": "16 avos de final",
      "channel": "SporTV / CazéTV",
      "stadium": "Levi's Stadium"
    },
    {
      "date": "2026-07-02",
      "time": "16:00",
      "home": "Espanha",
      "away": "Áustria",
      "competition": "Copa do Mundo 2026",
      "round": "16 avos de final",
      "channel": "Globo / SporTV / CazéTV",
      "stadium": "SoFi Stadium"
    },
    {
      "date": "2026-07-02",
      "time": "20:00",
      "home": "Cuiabá",
      "away": "América Mineiro",
      "competition": "Brasileirão Série B",
      "round": "Rodada 16",
      "channel": "A definir",
      "stadium": "Arena Pantanal"
    },
    {
      "date": "2026-07-02",
      "time": "20:00",
      "home": "Portugal",
      "away": "Croácia",
      "competition": "Copa do Mundo 2026",
      "round": "16 avos de final",
      "channel": "SporTV / CazéTV",
      "stadium": "BMO Field"
    },
    {
      "date": "2026-07-03",
      "time": "00:00",
      "home": "Suíça",
      "away": "Argélia",
      "competition": "Copa do Mundo 2026",
      "round": "16 avos de final",
      "channel": "CazéTV",
      "stadium": "BC Place"
    },
    {
      "date": "2026-07-03",
      "time": "15:00",
      "home": "Austrália",
      "away": "Egito",
      "competition": "Copa do Mundo 2026",
      "round": "16 avos de final",
      "channel": "Globo / CazéTV",
      "stadium": "AT&T Stadium"
    },
    {
      "date": "2026-07-03",
      "time": "19:00",
      "home": "Argentina",
      "away": "Cabo Verde",
      "competition": "Copa do Mundo 2026",
      "round": "16 avos de final",
      "channel": "Globo / CazéTV",
      "stadium": "Hard Rock Stadium"
    },
    {
      "date": "2026-07-03",
      "time": "21:00",
      "home": "Fortaleza",
      "away": "Ponte Preta",
      "competition": "Brasileirão Série B",
      "round": "Rodada 16",
      "channel": "A definir",
      "stadium": ""
    },
    {
      "date": "2026-07-03",
      "time": "22:30",
      "home": "Colômbia",
      "away": "Gana",
      "competition": "Copa do Mundo 2026",
      "round": "16 avos de final",
      "channel": "CazéTV",
      "stadium": "Arrowhead Stadium"
    }
  ]
}
